README.md
setup.cfg
setup.py
eHostess/UnitTests.py
eHostess/__init__.py
eHostess/Analysis/DocumentComparison.py
eHostess/Analysis/Metrics.py
eHostess/Analysis/Output.py
eHostess/Analysis/__init__.py
eHostess/Annotations/Document.py
eHostess/Annotations/MentionLevelAnnotation.py
eHostess/Annotations/__init__.py
eHostess/MongoDBInterface/MongoTools.py
eHostess/MongoDBInterface/__init__.py
eHostess/NotePreprocessing/Preprocessor.py
eHostess/NotePreprocessing/Testing.py
eHostess/NotePreprocessing/VerifyUniqueNames.py
eHostess/NotePreprocessing/__init__.py
eHostess/PyConTextInterface/PyConText.py
eHostess/PyConTextInterface/SentenceReconstructor.py
eHostess/PyConTextInterface/SentenceRepeatManager.py
eHostess/PyConTextInterface/__init__.py
eHostess/PyConTextInterface/SentenceSplitters/PyConTextBuiltinSplitter.py
eHostess/PyConTextInterface/SentenceSplitters/PyConTextInput.py
eHostess/PyConTextInterface/SentenceSplitters/SpacySplitter.py
eHostess/PyConTextInterface/SentenceSplitters/TargetSpanSplitter.py
eHostess/PyConTextInterface/SentenceSplitters/__init__.py
eHostess/PyConTextInterface/TargetsAndModifiers/modifiers.tsv
eHostess/PyConTextInterface/TargetsAndModifiers/targets.tsv
eHostess/Utilities/BagOfWords.py
eHostess/Utilities/__init__.py
eHostess/Utilities/utilities.py
eHostess/eHostInterface/KnowtatorReader.py
eHostess/eHostInterface/KnowtatorWriter.py
eHostess/eHostInterface/__init__.py
ehostess.egg-info/PKG-INFO
ehostess.egg-info/SOURCES.txt
ehostess.egg-info/dependency_links.txt
ehostess.egg-info/top_level.txt