Metadata-Version: 1.1
Name: ehostess
Version: 0.0.3
Summary: A toolkit for working with eHost, pyConText, and other annotation and NLP tools.
Home-page: https://github.com/MMontgomeryTaggart/eHostess
Author: Max Taggart
Author-email: max.taggart@utah.edu
License: MIT
Download-URL: https://github.com/MMontgomeryTaggart/eHostess/archive/0.0.3.tar.gz
Platform: UNKNOWN
